LICENSE
MANIFEST.in
README.rst
TODO.rst
setup.py
django_relationships.egg-info/PKG-INFO
django_relationships.egg-info/SOURCES.txt
django_relationships.egg-info/dependency_links.txt
django_relationships.egg-info/top_level.txt
relationships/__init__.py
relationships/admin.py
relationships/decorators.py
relationships/forms.py
relationships/listeners.py
relationships/models.py
relationships/urls.py
relationships/utils.py
relationships/views.py
relationships/fixtures/initial_data.json
relationships/locale/de/LC_MESSAGES/django.mo
relationships/locale/de/LC_MESSAGES/django.po
relationships/locale/en/LC_MESSAGES/django.mo
relationships/locale/en/LC_MESSAGES/django.po
relationships/migrations/0001_initial.py
relationships/migrations/0002_add_site_fk.py
relationships/migrations/0003_slugs_to_charfields.py
relationships/migrations/0004_add_site_to_unique_together.py
relationships/migrations/0005_add_weight_column.py
relationships/migrations/__init__.py
relationships/relationships_tests/__init__.py
relationships/relationships_tests/models.py
relationships/relationships_tests/tests.py
relationships/relationships_tests/urls.py
relationships/relationships_tests/fixtures/relationships.json
relationships/templates/404.html
relationships/templates/base.html
relationships/templates/relationships/confirm.html
relationships/templates/relationships/relationship_list.html
relationships/templates/relationships/success.html
relationships/templatetags/__init__.py
relationships/templatetags/relationship_tags.py