Metadata-Version: 1.1
Name: django-relationships
Version: 0.3.2
Summary: descriptive relationships between auth.User
Home-page: http://github.com/coleifer/django-relationships/tree/master
Author: Charles Leifer
Author-email: coleifer@gmail.com
License: UNKNOWN
Platform: UNKNOWN
Classifier: Development Status :: 4 - Beta
Classifier: Environment :: Web Environment
Classifier: Intended Audience :: Developers
Classifier: License :: OSI Approved :: MIT License
Classifier: Operating System :: OS Independent
Classifier: Programming Language :: Python
Classifier: Framework :: Django
